Metadata-Version: 2.1
Name: aliopts
Version: 0.0.2
Summary: A hyperparameter optimization framework
Home-page: UNKNOWN
Author: Ora Yang
Author-email: victor.xsyang@gmail.com
License: UNKNOWN
Platform: UNKNOWN
Classifier: Programming Language :: Python :: 3
Classifier: License :: OSI Approved :: MIT License
Classifier: Operating System :: OS Independent
Requires-Python: >=3.6
Requires-Dist: alembic
Requires-Dist: cliff
Requires-Dist: cmaes (>=0.6.0)
Requires-Dist: colorlog
Requires-Dist: joblib
Requires-Dist: numpy
Requires-Dist: packaging (>=20.0)
Requires-Dist: scipy (!=1.4.0)
Requires-Dist: sqlalchemy (>=1.1.0)
Requires-Dist: tqdm
